abstractruntime/__init__.py
abstractruntime/core/__init__.py
abstractruntime/core/config.py
abstractruntime/core/event_keys.py
abstractruntime/core/models.py
abstractruntime/core/policy.py
abstractruntime/core/runtime.py
abstractruntime/core/spec.py
abstractruntime/core/vars.py
abstractruntime/evidence/__init__.py
abstractruntime/evidence/recorder.py
abstractruntime/identity/__init__.py
abstractruntime/identity/fingerprint.py
abstractruntime/integrations/__init__.py
abstractruntime/integrations/abstractcore/__init__.py
abstractruntime/integrations/abstractcore/constants.py
abstractruntime/integrations/abstractcore/default_tools.py
abstractruntime/integrations/abstractcore/effect_handlers.py
abstractruntime/integrations/abstractcore/factory.py
abstractruntime/integrations/abstractcore/llm_client.py
abstractruntime/integrations/abstractcore/logging.py
abstractruntime/integrations/abstractcore/mcp_worker.py
abstractruntime/integrations/abstractcore/observability.py
abstractruntime/integrations/abstractcore/summarizer.py
abstractruntime/integrations/abstractcore/tool_executor.py
abstractruntime/memory/__init__.py
abstractruntime/memory/active_context.py
abstractruntime/memory/active_memory.py
abstractruntime/memory/compaction.py
abstractruntime/rendering/__init__.py
abstractruntime/rendering/agent_trace_report.py
abstractruntime/rendering/json_stringify.py
abstractruntime/scheduler/__init__.py
abstractruntime/scheduler/convenience.py
abstractruntime/scheduler/registry.py
abstractruntime/scheduler/scheduler.py
abstractruntime/storage/__init__.py
abstractruntime/storage/artifacts.py
abstractruntime/storage/base.py
abstractruntime/storage/in_memory.py
abstractruntime/storage/json_files.py
abstractruntime/storage/ledger_chain.py
abstractruntime/storage/observable.py
abstractruntime/storage/snapshots.py
abstractruntime-0.4.0.dist-info/METADATA
abstractruntime-0.4.0.dist-info/WHEEL
abstractruntime-0.4.0.dist-info/entry_points.txt
abstractruntime-0.4.0.dist-info/licenses/LICENSE
abstractruntime-0.4.0.dist-info/RECORD
