Metadata-Version: 2.4
Name: AbstractRuntime
Version: 0.4.0
Summary: AbstractRuntime: a durable graph runner designed to pair with AbstractCore.
Project-URL: AbstractCore (website), https://www.abstractcore.ai/
Project-URL: AbstractCore (GitHub), https://github.com/lpalbou/abstractruntime
Author: Laurent-Philippe Albou
License: MIT
License-File: LICENSE
Keywords: agents,checkpoint,durable,graph,llm,resume,workflow
Classifier: Development Status :: 1 - Planning
Classifier: Intended Audience :: Developers
Classifier: License :: OSI Approved :: MIT License
Classifier: Programming Language :: Python :: 3
Classifier: Programming Language :: Python :: 3 :: Only
Classifier: Programming Language :: Python :: 3.10
Classifier: Programming Language :: Python :: 3.11
Classifier: Programming Language :: Python :: 3.12
Classifier: Programming Language :: Python :: 3.13
Requires-Python: >=3.10
Provides-Extra: abstractcore
Requires-Dist: abstractcore>=2.6.8; extra == 'abstractcore'
Provides-Extra: mcp-worker
Requires-Dist: abstractcore[tools]>=2.6.8; extra == 'mcp-worker'
